shipyard_databricks/__init__.py
shipyard_databricks/cli/__init__.py
shipyard_databricks/cli/authtest.py
shipyard_databricks/cli/databricks_client.py
shipyard_databricks/cli/download.py
shipyard_databricks/cli/errors.py
shipyard_databricks/cli/move.py
shipyard_databricks/cli/remove.py
shipyard_databricks/cli/upload.py
shipyard_databricks/databricks.py
shipyard_databricks-0.1.0.dist-info/METADATA
shipyard_databricks-0.1.0.dist-info/WHEEL
shipyard_databricks-0.1.0.dist-info/RECORD
