Metadata-Version: 2.1
Name: shipyard-databricks
Version: 0.1.0
Summary: A local client for connecting and working with Databricks
License: Apache 2.0
Author: wrp801
Author-email: wespoulsen@gmail.com
Requires-Python: >=3.7,<3.10
Classifier: License :: Other/Proprietary License
Classifier: Programming Language :: Python :: 3
Classifier: Programming Language :: Python :: 3.7
Classifier: Programming Language :: Python :: 3.8
Classifier: Programming Language :: Python :: 3.9
Requires-Dist: databricks-cli (>=0.17.6,<0.18.0)
Requires-Dist: databricks-sdk (>=0.2.1,<0.3.0)
Requires-Dist: shipyard-templates (==0.5.0a0)
Requires-Dist: shipyard-utils (>=0.1.4,<0.2.0)
